{
  "PaymentConditionLink": "http://uvdata.dk",
  "GDPRConditionLink": "https://www.uvdata.dk/",
  "UseEnrollmentFee": true,
  "EnrollmentFee": 1.0,
  "NoFeeForSiblings": false,
  "NoFeeForSiblingsOnWaitList": false,
  "SchoolStart": [
    "2024/2025",
    "2025/2026",
    "2026/2027",
    "2027/2028",
    "2028/2029",
    "2029/2030",
    "2030/2031",
    "2031/2032",
    "2032/2033",
    "2033/2034",
    "2034/2035",
    "2035/2036",
    "2036/2037",
    "2037/2038",
    "2038/2039",
    "2039/2040",
    "2040/2041"
  ],
  "SchoolClasses": [9, 10],
  "MenuVisibleFromClass": 9,
  "KindergartenText": "Børnehave",
  "SpecialFieldText": "Ønsker SFO",
  "IsPrivateOrFreeSchool": true,
  "ReceiptFreeText": "Hermed bekræftes opskrivning på ventelisten - eksempel på fritekst.",
  "LineCourses": ["Linje 1", "Linje 2", "Linje 3"],
  "SpecialFields": [
    { "Name": "Samtykkeerklæring", "Selected": true },
    { "Name": "Må barnet fotograferes?", "Selected": true },
    { "Name": "Ønskes der plads i SFO", "Selected": false },
    { "Name": "Tysk i 7. kl", "Selected": true },
    { "Name": "Fransk i 7. kl", "Selected": false },
    { "Name": "Jeg har vedhæftet samtalearket", "Selected": false },
    { "Name": "Dansk statsborgerskab", "Selected": false },
    {
      "Name": "Er der sygdomme, kosthensyn eller andet skolen skal være opmærksom på",
      "Selected": false
    }
  ],
  "ClosedClasses": [],
  "SubHeading": "",
  "Name": "Test Skole",
  "Address": "Lauritzens Plads 1",
  "Zipcode": "9000",
  "City": "Aalborg",
  "Phone": "72287030",
  "Email": "nomail@uvdata.net",
  "ImageBase64": "/src/assets/uvdata.svg",
  "Styles": "",
  "WelcomeText": ""
}
